lib/__init__.py
lib/data.py
lib/metrics.py
lib/preprocessing.py
lib/simulation.py
lib/tempCodeRunnerFile.py
lib/utils.py
BacktestFramework-0.0.2.dist-info/LICENSE
BacktestFramework-0.0.2.dist-info/METADATA
BacktestFramework-0.0.2.dist-info/WHEEL
BacktestFramework-0.0.2.dist-info/top_level.txt
BacktestFramework-0.0.2.dist-info/RECORD
